{"events":[{"id":"2b7545a6-ebee-426c-b906-2329bc8d62bd","title":"팀 회의","date":"2025-10-20","startTime":"10:00","endTime":"11:00","description":"주간 팀 미팅","location":"회의실 A","category":"업무","repeat":{"type":"none","interval":0},"notificationTime":1},{"id":"09702fb3-a478-40b3-905e-9ab3c8849dcd","title":"점심 약속","date":"2025-10-21","startTime":"12:30","endTime":"13:30","description":"동료와 점심 식사","location":"회사 근처 식당","category":"개인","repeat":{"type":"none","interval":0},"notificationTime":1},{"id":"da3ca408-836a-4d98-b67a-ca389d07552b","title":"프로젝트 마감","date":"2025-10-25","startTime":"09:00","endTime":"18:00","description":"분기별 프로젝트 마감","location":"사무실","category":"업무","repeat":{"type":"none","interval":0},"notificationTime":1},{"id":"dac62941-69e5-4ec0-98cc-24c2a79a7f81","title":"생일 파티","date":"2025-10-28","startTime":"19:00","endTime":"22:00","description":"친구 생일 축하","location":"친구 집","category":"개인","repeat":{"type":"none","interval":0},"notificationTime":1},{"id":"80d85368-b4a4-47b3-b959-25171d49371f","title":"운동","date":"2025-10-22","startTime":"18:00","endTime":"19:00","description":"주간 운동","location":"헬스장","category":"개인","repeat":{"type":"none","interval":0},"notificationTime":1},{"id":"8c5eaedb-4574-4d74-bf93-ab5908f4186d","title":"","date":"","startTime":"","endTime":"","description":"","location":"","category":"업무","repeat":{"type":"none","interval":1},"notificationTime":10},{"id":"3be2ef78-4851-4940-9e34-1a2ea5ebca19","title":"","date":"2025-11-05","startTime":"","endTime":"","description":"","location":"","category":"업무","repeat":{"type":"none","interval":1},"notificationTime":10},{"id":"8a277bdd-9a8f-40d8-83d5-56dd75810a77","title":"","date":"2025-11-05","startTime":"","endTime":"","description":"","location":"","category":"업무","repeat":{"type":"none","interval":1},"notificationTime":10},{"id":"f74b5673-8df4-48f3-b216-f87c93eb7f41","title":"123","date":"2025-11-05","startTime":"10:53","endTime":"22:54","description":"","location":"","category":"업무","repeat":{"type":"daily","interval":1,"endDate":"2025-11-07","id":"83dd93ed-d16c-407c-9238-684158659851"},"notificationTime":10},{"id":"0dc4357e-21c2-471d-abc0-4cabaaf74ef0","title":"123","date":"2025-11-06","startTime":"10:53","endTime":"22:54","description":"","location":"","category":"업무","repeat":{"type":"daily","interval":1,"endDate":"2025-11-07","id":"83dd93ed-d16c-407c-9238-684158659851"},"notificationTime":10},{"id":"796a80a5-0fb4-4d67-ba46-3b4c58c391e0","title":"123","date":"2025-11-07","startTime":"10:53","endTime":"22:54","description":"","location":"","category":"업무","repeat":{"type":"daily","interval":1,"endDate":"2025-11-07","id":"83dd93ed-d16c-407c-9238-684158659851"},"notificationTime":10},{"id":"c9597792-d017-4e0c-9199-4e540afb04b1","title":"","date":"2025-11-05","startTime":"","endTime":"","description":"","location":"","category":"업무","repeat":{"type":"none","interval":1},"notificationTime":10}]}